vyze/__init__.py
vyze/access.py
vyze/client.py
vyze/data.py
vyze/skeleton.py
vyze/stream.py
vyze/universe.py
vyze/util.py
vyze/api/__init__.py
vyze/api/access.py
vyze/api/universe.py
vyze/client/__init__.py
vyze/client/client.py
vyze/client/pipe.py
vyze/cloud/__init__.py
vyze/cloud/access.py
vyze/cloud/universe.py
vyze/service/__init__.py
vyze/service/client.py
vyze/system/__init__.py
vyze/system/access.py
vyze/system/client.py
vyze/system/client_stream.py
vyze/system/resource.py
vyze/system/stream.py
vyze/system/stream_old.py
vyze/system/types.py
vyze/tests/__init__.py
vyze/tests/test_access.py
vyze/tests/test_client.py
vyze/tests/test_pipe.py
vyze/tests/test_resource.py
vyze/tests/test_service.py
vyze/tests/test_space.py
vyze/tests/test_stream.py
vyze/tests/test_system.py
vyze/tests/test_universe.py
vyze/tests/test_universe.yml
vyze/universe/__init__.py
vyze/universe/universe.py
vyze-0.1.14.dist-info/LICENSE.txt
vyze-0.1.14.dist-info/METADATA
vyze-0.1.14.dist-info/WHEEL
vyze-0.1.14.dist-info/top_level.txt
vyze-0.1.14.dist-info/RECORD
