Metadata-Version: 2.1
Name: vyze
Version: 0.1.14
Summary: Add a short description here!
Home-page: https://vyze.io
Author: Julian Matschinske
Author-email: julian.matschinske@bitspark.de
License: Apache License 2.0
Project-URL: Source, https://github.com/bitspark/vyze-python
Project-URL: Twitter, https://twitter.com/bitspark
Platform: any
Classifier: Development Status :: 4 - Beta
Classifier: Programming Language :: Python
License-File: LICENSE.txt
Requires-Dist: requests
Requires-Dist: websocket-client
Requires-Dist: pyyaml
Requires-Dist: importlib-metadata ; python_version < "3.8"
Provides-Extra: testing
Requires-Dist: setuptools ; extra == 'testing'
Requires-Dist: pytest ; extra == 'testing'
Requires-Dist: pytest-cov ; extra == 'testing'
